<?xml version="1.0" encoding="UTF-8"?>
<objects serializationModel="Studio.01.10.00">
    <object class="AudioFile" id="{047a0d1b-28ba-44fb-8429-0167759df475}">
        <property name="assetPath">
            <value>Music/BB_Music_v2_partC_tail.ogg</value>
        </property>
        <property name="isStreaming">
            <value>true</value>
        </property>
        <property name="frequencyInKHz">
            <value>48</value>
        </property>
        <property name="channelCount">
            <value>2</value>
        </property>
        <property name="length">
            <value>14.778770833333333</value>
        </property>
        <relationship name="masterAssetFolder">
            <destination>{70e25a8b-6aca-43d1-8ef1-f3fd4b1c35bd}</destination>
        </relationship>
    </object>
</objects>
